{
    "code": 0,
    "msg": "success",
    "data": {
        "types": [
            {
                "type": "其他",
                "num": 21037,
                "percent": 36.95
            },
            {
                "type": "超时未支付 //房东拒绝",
                "num": 17481,
                "percent": 30.71
            },
            {
                "type": "行程变更",
                "num": 7397,
                "percent": 12.99
            },
            {
                "type": "下错订单了",
                "num": 4978,
                "percent": 8.74
            },
            {
                "type": "超时未确认",
                "num": 3337,
                "percent": 5.86
            },
            {
                "type": "酒店无房",
                "num": 1916,
                "percent": 3.37
            },
            {
                "type": "联系不上房东",
                "num": 271,
                "percent": 0.48
            },
            {
                "type": "价格不符",
                "num": 224,
                "percent": 0.39
            },
            {
                "type": "对房屋不满意",
                "num": 183,
                "percent": 0.32
            },
            {
                "type": "对房东不满意",
                "num": 46,
                "percent": 0.08
            },
            {
                "type": "指定房间无房",
                "num": 17,
                "percent": 0.03
            },
            {
                "type": "接入系统成单失败",
                "num": 2,
                "percent": 0
            },
            {
                "type": "接入系统网络异常",
                "num": 1,
                "percent": 0
            }
        ],
        "nums": [
            {
                "num": 8628,
                "date": "2019-06-03"
            },
            {
                "num": 9385,
                "date": "2019-06-04"
            },
            {
                "num": 9544,
                "date": "2019-06-05"
            },
            {
                "num": 9426,
                "date": "2019-06-06"
            },
            {
                "num": 8319,
                "date": "2019-06-07"
            },
            {
                "num": 6283,
                "date": "2019-06-08"
            },
            {
                "num": 5341,
                "date": "2019-06-09"
            }
        ]
    }
}